[
    {
	"kind": "Furniture",
	"name": "Furniture",
        "render_color": "#000060", 

	"mass": 34.5,
	"static_friction": 0.07,
	"kinetic_friction": 0.05,
	"elasticity": 0.6,
	"buoyancy_volume_fill": 0.05,
	"surface": "Open"
    },

    {        
	"kind": "HumanHead",
	"name": "HumanHead",
	"render_color": "#006000", 

	"mass": 34.5,
	"static_friction": 0.1,
	"kinetic_friction": 0.1,
	"elasticity": 0.6,
	"buoyancy_volume_fill": 0.05,
	"surface": "Open"
    },

    {
	"kind": "HumanFeet",
	"name": "HumanFeet",
	"render_color": "#600000", 
	
	"mass": 34.5,
	"static_friction": 1.045,
	"kinetic_friction": 1.0,
	"elasticity": 0.6,
	"buoyancy_volume_fill": 0.03,
	"surface": "Open"
    }

]